{
  "@id": "dtmi:digitaltwins:org:generic:sco:scopro:Plant;1",
  "@type": "Interface",
  "contents": [
    {
      "@type": "Relationship",
      "description": {
        "en": "inversa de isResourceRoleOf Inverse of: isResourceRoleOf"
      },
      "minMultiplicity": 0,
      "name": "hasResourceRole",
      "target": "dtmi:digitaltwins:org:generic:sco:scopro:Production_Site;1"
    }
  ],
  "displayName": {
    "en": "Plant"
  },
  "extends": "dtmi:digitaltwins:org:generic:sco:scopro:Facility;1",
  "@context": "dtmi:dtdl:context;2"
}